License.md
ipytest/__init__.py
ipytest/_config.py
ipytest/_impl.py
ipytest/cov.py
ipytest-0.14.1.dist-info/METADATA
ipytest-0.14.1.dist-info/WHEEL
ipytest-0.14.1.dist-info/RECORD
