Metadata-Version: 2.1
Name: ipytest
Version: 0.14.1
Summary: Unit tests in IPython notebooks
License: MIT
Author: Christopher Prohm
Author-email: mail@cprohm.de
Requires-Python: >=3.8,<4
Classifier: Development Status :: 4 - Beta
Classifier: Intended Audience :: Developers
Classifier: License :: OSI Approved :: MIT License
Classifier: Programming Language :: Python :: 3
Classifier: Programming Language :: Python :: 3.8
Classifier: Programming Language :: Python :: 3.9
Classifier: Programming Language :: Python :: 3.10
Classifier: Programming Language :: Python :: 3.11
Classifier: Programming Language :: Python :: 3.12
Classifier: Topic :: Software Development :: Testing
Requires-Dist: ipython
Requires-Dist: packaging
Requires-Dist: pytest (>=5.4)
